pioreactor_logs2discord/LEADER_ONLY
pioreactor_logs2discord/__init__.py
pioreactor_logs2discord/additional_config.ini
pioreactor_logs2discord/post_install.sh
pioreactor_logs2discord/pre_uninstall.sh
pioreactor_logs2discord-0.3.0.dist-info/LICENSE
pioreactor_logs2discord-0.3.0.dist-info/METADATA
pioreactor_logs2discord-0.3.0.dist-info/WHEEL
pioreactor_logs2discord-0.3.0.dist-info/entry_points.txt
pioreactor_logs2discord-0.3.0.dist-info/top_level.txt
pioreactor_logs2discord-0.3.0.dist-info/RECORD
