Metadata-Version: 2.1
Name: pioreactor-logs2discord
Version: 0.3.0
Summary: Push logs generated by Pioreactors to your Discord workspace
Home-page: https://github.com/Pioreactor/pioreactor-logs2discord
Author: Pioreactor
Author-email: hello@pioreactor.com
License: MIT
License-File: LICENSE
